jacobs_jinja_too-0.2.11.dist-info/licenses/LICENSE
jacobsjinjatoo/__init__.py
jacobsjinjatoo/_version.py
jacobsjinjatoo/filewriter.py
jacobsjinjatoo/stringmanip.py
jacobsjinjatoo/templator.py
jacobs_jinja_too-0.2.11.dist-info/METADATA
jacobs_jinja_too-0.2.11.dist-info/WHEEL
jacobs_jinja_too-0.2.11.dist-info/top_level.txt
jacobs_jinja_too-0.2.11.dist-info/RECORD
