Metadata-Version: 2.4
Name: jacobs-jinja-too
Version: 0.2.11
Summary: Simple wrapper around jinja2 templating
Author-email: Jacob Brunson <pypi@jacobbrunson.com>
License-Expression: LGPL-2.0
Project-URL: Homepage, http://github.com/pearmaster/jacobs-jinja-too
Requires-Python: >=3.9
License-File: LICENSE
Requires-Dist: jinja-markdown>=1.210911
Requires-Dist: jinja2>=3.1.6
Dynamic: license-file
